{
  "meta": {
    "url": "https://www.binance.com/bapi/futures/v1/private/future/user-data/transaction-history",
    "method": "POST",
    "pathname": "/bapi/futures/v1/private/future/user-data/transaction-history",
    "query": {},
    "postData": {
      "startTime": 1767196800000,
      "endTime": 1769183999998,
      "page": 1,
      "rows": 200
    },
    "timestamp": 1769148158877,
    "category": "transaction_history"
  },
  "response": {
    "code": "000000",
    "message": null,
    "messageDetail": null,
    "data": [
      {
        "id": "90161654003738_COMMISSION",
        "tranId": 90161654003738,
        "asset": "USDT",
        "balancetype": "COMMISSION",
        "balanceDelta": -0.00262752,
        "balanceTypeStr": "COMMISSION",
        "balanceDeltaStr": "-0.00262752",
        "balanceInfo": "654003738",
        "time": 1769145653000,
        "symbol": "TRXUSDT"
      },
      {
        "id": "90160653511142_COMMISSION",
        "tranId": 90160653511142,
        "asset": "USDT",
        "balancetype": "COMMISSION",
        "balanceDelta": -0.00251387,
        "balanceTypeStr": "COMMISSION",
        "balanceDeltaStr": "-0.00251387",
        "balanceInfo": "653511142",
        "time": 1768989518000,
        "symbol": "TRXUSDT"
      },
      {
        "id": "90160653511142_REALIZED_PNL",
        "tranId": 90160653511142,
        "asset": "USDT",
        "balancetype": "REALIZED_PNL",
        "balanceDelta": -0.28645,
        "balanceTypeStr": "REALIZED_PNL",
        "balanceDeltaStr": "-0.28645000",
        "balanceInfo": "653511142",
        "time": 1768989518000,
        "symbol": "TRXUSDT"
      }
    ],
    "success": true
  }
}